[
    {
        "id": 5,
        "title": "Nâng mức cho vay chương trình hỗ trợ tạo việc làm, duy trì, mở rộng việc làm",
        "category": "Tin Hoạt Động",
        "description": "Nâng mức cho vay chương trình hỗ trợ tạo việc làm, duy trì, mở rộng việc làm",
        "pdf_url": "",
        "audio_url": "https://raw.githubusercontent.com/snnmt/radiomattran/main/amthanh/radio_1770862588.mp3",
        "image_url": "https://raw.githubusercontent.com/snnmt/radiomattran/main/hinhanh/up_1770862587.png",
        "last_updated": "12/02/2026"
    },
    {
        "id": 3,
        "title": "Tuyên truyền những điểm mới của Luật Đất đai (sửa đổi)",
        "category": "Pháp Luật",
        "description": "Phổ biến các quy định mới liên quan đến quyền lợi của người dân khi thu hồi đất.",
        "pdf_url": "https://raw.githubusercontent.com/snnmt/radiomattran/main/tailieu/luatdatdai_tomtat.pdf",
        "audio_url": "https://www.soundhelix.com/examples/mp3/SoundHelix-Song-1.mp3",
        "image_url": "https://raw.githubusercontent.com/snnmt/radiomattran/main/hinhanh/tuyentruyenphapluat.jpg",
        "last_updated": "10/02/2026"
    },
    {
        "id": 2,
        "title": "Ra quân dọn dẹp vệ sinh tuyến đường hoa kiểu mẫu",
        "category": "Nông Thôn Mới",
        "description": "Mặt trận xã phối hợp các đoàn thể ra quân thực hiện tiêu chí môi trường sáng - xanh - sạch - đẹp.",
        "pdf_url": "",
        "audio_url": "https://raw.githubusercontent.com/snnmt/radiokhuyennong/main/amthanh/testamthanhkythuatcanhtacbuoi.mp3",
        "image_url": "https://raw.githubusercontent.com/snnmt/radiomattran/main/hinhanh/nongthonmoi.jpg",
        "last_updated": "08/02/2026"
    }
]